t2s/__init__.py
t2s/cli.py
t2s/lang.py
t2s/langs.py
t2s/tts.py
t2s/utils.py
t2s/tests/__init__.py
t2s/tests/test_cli.py
t2s/tests/test_lang.py
t2s/tests/test_tts.py
t2s/tests/test_utils.py
t2s/tokenizer/__init__.py
t2s/tokenizer/core.py
t2s/tokenizer/pre_processors.py
t2s/tokenizer/symbols.py
t2s/tokenizer/tokenizer_cases.py
t2s-2021.1.dist-info/LICENSE
t2s-2021.1.dist-info/METADATA
t2s-2021.1.dist-info/WHEEL
t2s-2021.1.dist-info/top_level.txt
t2s-2021.1.dist-info/RECORD
