Metadata-Version: 2.1
Name: t2s
Version: 2021.1
Summary: Python based toolkit for writing Command-Line Interface applications
Home-page: https://quo.rtfd.io
Author: Gerrishon Sirere
Author-email: secretum.inc@pm.me
Maintainer: Secretum Inc.
Maintainer-email: secretum.inc@pm.me
License: MIT
Project-URL: Donate, https://tinyurl.com/ygaj5fwj
Project-URL: Documentation, https://quo.rtfd.io
Project-URL: Changes, https://quo.readthedocs.io/en/latest/changes.html
Project-URL: Source Code, https://github.com/secretum-inc/quo
Project-URL: Issue Tracker, https://github.com/secretum-inc/quo/issues/
Project-URL: Twitter, https://twitter.com/secretum_inc
Project-URL: Chat, https://gitter.im/secretum-inc
Platform: UNKNOWN
Classifier: Development Status :: 5 - Production/Stable
Classifier: Intended Audience :: Developers
Classifier: License :: OSI Approved :: MIT License
Classifier: Operating System :: OS Independent
Classifier: Programming Language :: Python
Requires-Python: >=3.6.1
Requires-Dist: quo ; platform_system == "Windows"
Requires-Dist: six ; python_version < "3.8"
